第五題/design.sv
module Ex(D,Q);
input [3:0] D; //四位元輸入
output [1:0] Q; //二位元輸出
reg [1:0] Q; //宣告為暫存器資料
always@ (D)
    casex(D)
        4'b1000 : Q = 3;
        4'bx100 : Q = 2;
        4'bxx10 : Q = 1;
        default : Q = 0;
    endcase
endmodule

第五題/testbench.sv
`timescale 1ns/1ns
`include "design.sv"
module Test();

    reg [3:0] D;
    wire [1:0] Q;
    Ex uut(
        .D(D),
        .Q(Q)
    );

    initial begin
        D = 4'b0000;
        #10 D = 4'b0001;
        #10 D = 4'b0010;
        #10 D = 4'b0011;
        #10 D = 4'b0100;
        #10 D = 4'b0101;
        #10 D = 4'b0110;
        #10 D = 4'b0111;
        #10 D = 4'b1000;
        #10 D = 4'b1001;
        #10 D = 4'b1010;
        #10 D = 4'b1011;
        #10 D = 4'b1100;
        #10 D = 4'b1101;
        #10 D = 4'b1110;
        #10 D = 4'b1111;
        #10 $finish;
    end

    initial begin

        $dumpfile("dump.vcd");
        $dumpvars(0);
    end


endmodule

第五題/dump.vcd
$date
	Sun Jun 11 10:13:54 2023
$end
$version
	Icarus Verilog
$end
$timescale
	1ns
$end
$scope module Test $end
$var wire 2 ! Q [1:0] $end
$var reg 4 " D [3:0] $end
$scope module uut $end
$var wire 4 # D [3:0] $end
$var reg 2 $ Q [1:0] $end
$upscope $end
$upscope $end
$enddefinitions $end
#0
$dumpvars
b0 $
b0 #
b0 "
b0 !
$end
#10
b1 "
b1 #
#20
b1 !
b1 $
b10 "
b10 #
#30
b0 !
b0 $
b11 "
b11 #
#40
b10 !
b10 $
b100 "
b100 #
#50
b0 !
b0 $
b101 "
b101 #
#60
b1 !
b1 $
b110 "
b110 #
#70
b0 !
b0 $
b111 "
b111 #
#80
b11 !
b11 $
b1000 "
b1000 #
#90
b0 !
b0 $
b1001 "
b1001 #
#100
b1 !
b1 $
b1010 "
b1010 #
#110
b0 !
b0 $
b1011 "
b1011 #
#120
b10 !
b10 $
b1100 "
b1100 #
#130
b0 !
b0 $
b1101 "
b1101 #
#140
b1 !
b1 $
b1110 "
b1110 #
#150
b0 !
b0 $
b1111 "
b1111 #
