第三題/design.sv
module Ex(A,B,C,F);
input A,B,C;
output F;
wire c1; // c1為A與B運算後之中繼符號
assign c1 = A & B;
assign F = c1 & C;
endmodule

第三題/testbench.sv
`include "design.sv"
`timescale 1ns/1ns
module Test();

    reg A,B,C;
    wire F;


    Ex uut(
        .A(A),
        .B(B),
        .C(C),
        .F(F)
    );

    initial begin
        A = 0;
        B = 0;
        C = 0;
        #100;
        A = 0;
        B = 0;
        C = 1;
        #100;
        A = 0;
        B = 1;
        C = 0;
        #100;
        A = 0;
        B = 1;
        C = 1;
        #100;
        A = 1;
        B = 0;
        C = 0;
        #100;
        A = 1;
        B = 0;
        C = 1;
        #100;
        A = 1;
        B = 1;
        C = 0;
        #100;
        A = 1;
        B = 1;
        C = 1;
        #100;
    end

    initial begin
        $dumpfile("dump.vcd");
        $dumpvars(0);
    end
endmodule

第三題/dump.vcd
$date
	Sun Jun 11 00:40:21 2023
$end
$version
	Icarus Verilog
$end
$timescale
	1ns
$end
$scope module Test $end
$var wire 1 ! F $end
$var reg 1 " A $end
$var reg 1 # B $end
$var reg 1 $ C $end
$scope module uut $end
$var wire 1 " A $end
$var wire 1 # B $end
$var wire 1 $ C $end
$var wire 1 ! F $end
$var wire 1 % c1 $end
$upscope $end
$upscope $end
$enddefinitions $end
#0
$dumpvars
0%
0$
0#
0"
0!
$end
#100
1$
#200
0$
1#
#300
1$
#400
0$
0#
1"
#500
1$
#600
1%
0$
1#
#700
1!
1$
